examples/__init__.py
examples/communication/__init__.py
examples/communication/service.py
examples/flask-leader/__init__.py
examples/flask-leader/server.py
qcluster/__init__.py
qcluster/communication.py
qcluster/consensus.py
qcluster/qcluster.py
qcluster/registry.py
qcluster/utils.py
QCluster-0.0.5.dist-info/LICENSE
QCluster-0.0.5.dist-info/METADATA
QCluster-0.0.5.dist-info/WHEEL
QCluster-0.0.5.dist-info/top_level.txt
QCluster-0.0.5.dist-info/RECORD
