Metadata-Version: 2.1
Name: QCluster
Version: 0.0.5
Summary: An SDK to enable quick clustering of microservices.
Home-page: https://github.com/QsonLabs/qcluster
Author: Aaron Rohrbaugh + (See GitHub)
Author-email: chriso@qsonlabs.com
Maintainer: Chris O'Connor
Maintainer-email: chriso@qsonlabs.com
License: Apache License 2.0
Platform: UNKNOWN
Classifier: Development Status :: 3 - Alpha
Classifier: Framework :: Flake8
Classifier: Framework :: Pytest
Classifier: Framework :: tox
Classifier: Intended Audience :: Developers
Classifier: Intended Audience :: System Administrators
Classifier: License :: OSI Approved :: Apache Software License
Classifier: Natural Language :: English
Classifier: Operating System :: OS Independent
Classifier: Programming Language :: Python :: 3
Classifier: Programming Language :: Python :: 3.8
Classifier: Topic :: System :: Clustering
Classifier: Topic :: System :: Distributed Computing
Requires-Python: >=3.8
Requires-Dist: aiohttp
